{
    "wave": {
        "version_id": "M",
        "wave_id": "M-PD",
        "subject_number": 30
    },

    "stimuli": {
        "exp_stimuli_dir": "stimuli/exp_stimuli_pilot",
        "dist_stimuli_dir": "stimuli/dist_stimuli_pilot", 
        "n_set_ids": 165,
        "excluded_set_ids": [18, 33, 66, 93, 120, 159],
        "practice_set_ids": [13, 19, 30]
    },

    "vision_experiment": {
        "vision_trials": 177,
        "enable_button_after": 1200,
        "ncatch": 20, 
        "inter_trial_delay": 150
    },

    "memory_experiment": {
        "encoding_conditions": ["mixed", "semantic", "visual"],
        "load": 3,
        "practice_trials": 3,
        "wm_trials": 156, 
        "wm_block1_trials": 60,
        "wm_block2_trials": 60,
        "wm_block3_trials": 36,
        "lm_trials": 120, 
        "ncatch": 18, 
        "serial": 0
    },

    "timing": {
        "encoding_times": [700,1200,1700,2200], 
        "memory_delay": 3000,
        "wm_inter_trial_delay": 2500,
        "lm_inter_trial_delay": 2000,
        "wm_isi": 200,
        "catch_delay": 750,
        "encoding_time_catch": 3000
    },
    
    "spatial": {
        "radius_x": 80,
        "radius_y": 80,
        "button_x": 70,
        "button_y": 290
    },
    
    "break": {
        "duration": 120000
    },
    
    "countdown": {
        "interval": 1000
    },

    "distractor": {
        "initial_number": 100,
        "random_min": 2,
        "random_max": 6,
        "delay_time": 1000,
        "stimulus_time": 3000,
        "feedback_timeout": 10000,
        "rounds": 3,
        "operations_per_round": 5
    },

    "feedback": {
        "duration": 10000
    }
}